yrouter/__init__.py
yrouter/constants.py
yrouter/converters.py
yrouter/exceptions.py
yrouter/match.py
yrouter/route.py
yrouter/route_node.py
yrouter/router.py
yrouter/utils.py
yrouter-1.1.0.dist-info/LICENSE
yrouter-1.1.0.dist-info/METADATA
yrouter-1.1.0.dist-info/WHEEL
yrouter-1.1.0.dist-info/top_level.txt
yrouter-1.1.0.dist-info/RECORD
