Metadata-Version: 2.1
Name: yrouter
Version: 1.1.0
Summary: A URL routing library.
Home-page: https://github.com/tijani-dia/yrouter/
Author: Tidiane Dia
Author-email: tidiane.dia@therookiecoder.com
License: BSD-3-Clause
Project-URL: Source, https://github.com/tijani-dia/yrouter/
Project-URL: Issue tracker, https://github.com/tijani-dia/yrouter/issues/
Platform: UNKNOWN
Classifier: Development Status :: 3 - Alpha
Classifier: Environment :: Web Environment
Classifier: Intended Audience :: Developers
Classifier: License :: OSI Approved :: BSD License
Classifier: Programming Language :: Python :: 3
Classifier: Programming Language :: Python :: 3 :: Only
Classifier: Programming Language :: Python :: 3.9
Classifier: Programming Language :: Python :: 3.10
Classifier: Topic :: Internet :: WWW/HTTP
Requires-Python: >=3.9
License-File: LICENSE
Provides-Extra: build
Requires-Dist: twine ; extra == 'build'
Requires-Dist: check-wheel-contents ; extra == 'build'
Provides-Extra: test
Requires-Dist: black ; extra == 'test'
Requires-Dist: isort ; extra == 'test'
Requires-Dist: flake8 ; extra == 'test'
Requires-Dist: pytest ; extra == 'test'
Requires-Dist: pytest-cov ; extra == 'test'
